slipoframes/__init__.py
slipoframes/__version__.py
slipoframes/context.py
slipoframes/model.py
slipoframes/utils.py
slipoframes/templates/iframe.html.j2
slipoframes/templates/workflow.html.j2
slipoframes/templates/css/workflow.css.j2
slipoframes/templates/js/workflow.js.j2
slipoframes-0.2.4.dist-info/LICENSE
slipoframes-0.2.4.dist-info/METADATA
slipoframes-0.2.4.dist-info/WHEEL
slipoframes-0.2.4.dist-info/top_level.txt
slipoframes-0.2.4.dist-info/RECORD
