Metadata-Version: 2.1
Name: slipoframes
Version: 0.2.4
Summary: SLIPO API client for Jupyter notebooks
Home-page: https://github.com/SLIPO-EU/slipo-frames
Author: Yannis Kouvaras
Author-email: jkouvar@imis.athena-innovation.gr
License: Apache Software License
Keywords: poi linked-data point-of-interest data-integration jupyter-notebook
Platform: UNKNOWN
Classifier: Programming Language :: Python :: 3
Classifier: Intended Audience :: Developers
Classifier: License :: OSI Approved :: Apache Software License
Classifier: Operating System :: OS Independent
Requires-Python: >=3
Requires-Dist: jinja2 (>=2.10)
Requires-Dist: pandas (>=0.24.2)
Requires-Dist: slipo (>=0.1.5)
Requires-Dist: IPython (>=6.0.0) ; python_version >= "3.4"
